[{"image": "0653.png", "verified": false, "annotations": [{"label": "disorganized", "coordinates": {"x": 18.35504885993487, "y": 168.6742671009772, "width": 36.71009771986974, "height": 70.0}}, {"label": "disorganized", "coordinates": {"x": 139.21009771986974, "y": 139.6742671009772, "width": 37.0, "height": 53.999999999999986}}, {"label": "disorganized", "coordinates": {"x": 280.35504885993487, "y": 133.6742671009772, "width": 39.28990228013026, "height": 53.999999999999986}}, {"label": "disorganized", "coordinates": {"x": 60.21009771986974, "y": 171.1742671009772, "width": 39.0, "height": 73.0}}, {"label": "disorganized", "coordinates": {"x": 136.71009771986974, "y": 246.1742671009772, "width": 46.0, "height": 41.0}}]}]