[{"image": "0754.png", "verified": false, "annotations": [{"label": "disorganized", "coordinates": {"x": 179.71009771986974, "y": 220.1742671009772, "width": 28.0, "height": 37.0}}, {"label": "disorganized", "coordinates": {"x": 230.71009771986974, "y": 205.1742671009772, "width": 12.0, "height": 33.0}}, {"label": "disorganized", "coordinates": {"x": 64.71009771986974, "y": 264.1742671009772, "width": 28.0, "height": 25.0}}, {"label": "disorganized", "coordinates": {"x": 108.71009771986974, "y": 185.1742671009772, "width": 108.0, "height": 31.0}}]}]