[{"image": "0006.png", "verified": false, "annotations": [{"label": "Empty", "coordinates": {"x": 187.01990632318507, "y": 174.7658079625293, "width": 63.0, "height": 60.0}}, {"label": "Empty", "coordinates": {"x": 131.01990632318507, "y": 246.26580796252932, "width": 25.0, "height": 55.0}}, {"label": "Empty", "coordinates": {"x": 104.01990632318505, "y": 192.2658079625293, "width": 19.0, "height": 65.0}}, {"label": "Disorganized", "coordinates": {"x": 266.51990632318507, "y": 115.2658079625293, "width": 62.0, "height": 51.0}}, {"label": "Disorganized", "coordinates": {"x": 66.51990632318505, "y": 108.7658079625293, "width": 34.0, "height": 48.0}}, {"label": "Disorganized", "coordinates": {"x": 167.51990632318507, "y": 109.7658079625293, "width": 16.0, "height": 50.0}}, {"label": "Disorganized", "coordinates": {"x": 198.51990632318507, "y": 110.7658079625293, "width": 16.0, "height": 50.0}}, {"label": "Disorganized", "coordinates": {"x": 101.51990632318505, "y": 36.765807962529294, "width": 20.0, "height": 60.0}}]}]