[{"image": "0045.png", "verified": false, "annotations": [{"label": "Empty", "coordinates": {"x": 16.019906323185054, "y": 171.2658079625293, "width": 29.0, "height": 21.0}}, {"label": "Empty", "coordinates": {"x": 42.519906323185054, "y": 140.7658079625293, "width": 20.0, "height": 18.0}}, {"label": "Empty", "coordinates": {"x": 62.019906323185054, "y": 251.76580796252932, "width": 13.0, "height": 18.0}}, {"label": "Disorganized", "coordinates": {"x": 105.51990632318505, "y": 182.7658079625293, "width": 36.0, "height": 18.0}}, {"label": "Disorganized", "coordinates": {"x": 152.51990632318507, "y": 248.76580796252932, "width": 52.0, "height": 22.0}}, {"label": "Disorganized", "coordinates": {"x": 198.01990632318507, "y": 250.26580796252932, "width": 13.0, "height": 19.0}}, {"label": "Empty", "coordinates": {"x": 128.51990632318507, "y": 184.2658079625293, "width": 8.0, "height": 17.0}}, {"label": "Disorganized", "coordinates": {"x": 139.51990632318507, "y": 213.2658079625293, "width": 16.0, "height": 17.0}}, {"label": "Disorganized", "coordinates": {"x": 245.01990632318507, "y": 246.76580796252932, "width": 21.0, "height": 24.0}}, {"label": "Disorganized", "coordinates": {"x": 211.01990632318507, "y": 207.7658079625293, "width": 15.0, "height": 14.0}}, {"label": "Disorganized", "coordinates": {"x": 92.51990632318505, "y": 124.2658079625293, "width": 14.0, "height": 19.0}}]}]