[
    {
        "image": "0779.png",
        "verified": false,
        "annotations": [
            {
                "label": "Disorganized",
                "coordinates": {
                    "x": 253.71009771986974,
                    "y": 227.1742671009772,
                    "width": 10.0,
                    "height": 17.0
                }
            },
            {
                "label": "Disorganized",
                "coordinates": {
                    "x": 114.71009771986974,
                    "y": 209.1742671009772,
                    "width": 12.0,
                    "height": 25.0
                }
            },
            {
                "label": "Disorganized",
                "coordinates": {
                    "x": 158.71009771986974,
                    "y": 203.6742671009772,
                    "width": 10.0,
                    "height": 24.0
                }
            },
            {
                "label": "Disorganized",
                "coordinates": {
                    "x": 54.21009771986974,
                    "y": 234.1742671009772,
                    "width": 11.0,
                    "height": 21.0
                }
            },
            {
                "label": "Disorganized",
                "coordinates": {
                    "x": 196.21009771986974,
                    "y": 237.6742671009772,
                    "width": 13.0,
                    "height": 24.0
                }
            }
        ]
    }
]