[{"image": "1296.png", "verified": false, "annotations": [{"label": "Empty", "coordinates": {"x": 130.51990632318507, "y": 194.2658079625293, "width": 20.000000000000014, "height": 25.0}}, {"label": "Empty", "coordinates": {"x": 70.51990632318505, "y": 280.7658079625293, "width": 54.0, "height": 20.0}}, {"label": "Empty", "coordinates": {"x": 172.51990632318507, "y": 193.2658079625293, "width": 20.0, "height": 23.0}}, {"label": "Empty", "coordinates": {"x": 223.01990632318507, "y": 191.7658079625293, "width": 27.0, "height": 26.0}}, {"label": "Empty", "coordinates": {"x": 169.01990632318507, "y": 104.2658079625293, "width": 31.0, "height": 19.0}}, {"label": "Empty", "coordinates": {"x": 132.51990632318507, "y": 70.2658079625293, "width": 26.000000000000014, "height": 22.999999999999993}}, {"label": "Disorganized", "coordinates": {"x": 151.51990632318507, "y": 192.2658079625293, "width": 20.0, "height": 29.0}}, {"label": "Disorganized", "coordinates": {"x": 180.01990632318507, "y": 222.7658079625293, "width": 25.0, "height": 22.0}}]}]