[{"image": "0044.png", "verified": false, "annotations": [{"label": "Empty Shelf", "coordinates": {"x": 21.019906323185054, "y": 84.2658079625293, "width": 17.0, "height": 31.0}}, {"label": "Empty Shelf", "coordinates": {"x": 43.019906323185054, "y": 83.7658079625293, "width": 15.0, "height": 32.0}}, {"label": "Empty Shelf", "coordinates": {"x": 285.51990632318507, "y": 130.7658079625293, "width": 12.0, "height": 28.0}}, {"label": "Empty Shelf", "coordinates": {"x": 79.51990632318505, "y": 172.7658079625293, "width": 10.0, "height": 24.0}}, {"label": "Empty Shelf", "coordinates": {"x": 234.01990632318507, "y": 39.2658079625293, "width": 17.0, "height": 29.0}}]}]