[{"image": "0516.png", "verified": false, "annotations": [{"label": "Empty Shelf", "coordinates": {"x": 69.51990632318505, "y": 16.2658079625293, "width": 64.0, "height": 27.0}}, {"label": "Empty Shelf", "coordinates": {"x": 214.51990632318507, "y": 88.2658079625293, "width": 112.0, "height": 54.99999999999999}}, {"label": "Empty Shelf", "coordinates": {"x": 217.51990632318507, "y": 170.2658079625293, "width": 76.0, "height": 59.0}}, {"label": "Empty Shelf", "coordinates": {"x": 89.51990632318505, "y": 174.2658079625293, "width": 32.0, "height": 53.0}}, {"label": "Empty Shelf", "coordinates": {"x": 140.51990632318507, "y": 176.7658079625293, "width": 22.0, "height": 54.0}}, {"label": "Empty Shelf", "coordinates": {"x": 83.01990632318507, "y": 248.26580796252932, "width": 99.00000000000001, "height": 61.00000000000003}}, {"label": "Empty Shelf", "coordinates": {"x": 218.01990632318507, "y": 248.26580796252932, "width": 51.0, "height": 63.00000000000003}}, {"label": "Empty Shelf", "coordinates": {"x": 16.019906323185054, "y": 136.7658079625293, "width": 31.0, "height": 44.0}}, {"label": "Empty Shelf", "coordinates": {"x": 15.519906323185054, "y": 220.26580796252932, "width": 30.0, "height": 93.00000000000003}}, {"label": "Empty Shelf", "coordinates": {"x": 288.25995316159253, "y": 100.7658079625293, "width": 23.48009367681493, "height": 76.0}}]}]